planutils/__init__.py
planutils/manifest_converter.py
planutils/package_installation.py
planutils/server.py
planutils/settings.py
planutils/packages/README.md
planutils/packages/TEMPLATE/install
planutils/packages/TEMPLATE/manifest.json
planutils/packages/TEMPLATE/run
planutils/packages/TEMPLATE/uninstall
planutils/packages/TEMPLATE/SERVICE_TEMPLATE/planner.json
planutils/packages/cerberus/install
planutils/packages/cerberus/manifest.json
planutils/packages/cerberus/run
planutils/packages/cerberus/uninstall
planutils/packages/cerberus-agl/install
planutils/packages/cerberus-agl/manifest.json
planutils/packages/cerberus-agl/run
planutils/packages/cerberus-agl/uninstall
planutils/packages/cerberus-sat/install
planutils/packages/cerberus-sat/manifest.json
planutils/packages/cerberus-sat/run
planutils/packages/cerberus-sat/uninstall
planutils/packages/cpddl/install
planutils/packages/cpddl/manifest.json
planutils/packages/cpddl/run
planutils/packages/cpddl/uninstall
planutils/packages/cpor/Dockerfile
planutils/packages/cpor/install
planutils/packages/cpor/manifest.json
planutils/packages/cpor/run
planutils/packages/cpor/uninstall
planutils/packages/delfi/install
planutils/packages/delfi/manifest.json
planutils/packages/delfi/run
planutils/packages/delfi/uninstall
planutils/packages/downward/install
planutils/packages/downward/manifest.json
planutils/packages/downward/run
planutils/packages/downward/uninstall
planutils/packages/dual-bfws-fdparser/install
planutils/packages/dual-bfws-fdparser/manifest.json
planutils/packages/dual-bfws-fdparser/run
planutils/packages/dual-bfws-fdparser/uninstall
planutils/packages/dual-bfws-ffparser/install
planutils/packages/dual-bfws-ffparser/manifest.json
planutils/packages/dual-bfws-ffparser/run
planutils/packages/dual-bfws-ffparser/uninstall
planutils/packages/eas/install
planutils/packages/eas/manifest.json
planutils/packages/eas/run
planutils/packages/eas/uninstall
planutils/packages/enhsp/install
planutils-0.10.19.dist-info/licenses/LICENSE
planutils-0.10.19.dist-info/METADATA
planutils-0.10.19.dist-info/WHEEL
planutils-0.10.19.dist-info/top_level.txt
planutils-0.10.19.dist-info/RECORD
