Metadata-Version: 2.4
Name: planutils
Version: 0.10.19
Summary: General library for setting up linux-based environments for developing, running, and evaluating planners.
Home-page: https://github.com/AI-Planning/planutils
Author: 
Author-email: 
License: MIT
Classifier: Programming Language :: Python :: 3
Classifier: License :: OSI Approved :: MIT License
Classifier: Operating System :: POSIX :: Linux
Requires-Python: >=3.6
License-File: LICENSE
Requires-Dist: requests
Dynamic: classifier
Dynamic: description
Dynamic: description-content-type
Dynamic: home-page
Dynamic: license
Dynamic: license-file
Dynamic: requires-dist
Dynamic: requires-python
Dynamic: summary
